djino/__init__.py
djino-0.0.0.dist-info/METADATA
djino-0.0.0.dist-info/WHEEL
djino-0.0.0.dist-info/RECORD
