Metadata-Version: 2.1
Name: djino
Version: 0.0.0
Summary: A magical tool to craft numerical simulations
Author: altar31
Author-email: damien.sicard31@gmail.com
Requires-Python: >=3.10,<4.0
Classifier: Programming Language :: Python :: 3
Classifier: Programming Language :: Python :: 3.10
Classifier: Programming Language :: Python :: 3.11
Requires-Dist: bokeh (>=3.1.0,<4.0.0)
Requires-Dist: click (>=8.1.3,<9.0.0)
Requires-Dist: pyvista (>=0.38.5,<0.39.0)
Requires-Dist: streamlit (>=1.21.0,<2.0.0)
